{
    "title": "Thanksgiving at Macy's",
    "description": "Use Martha Stewart Harvest Collection for Thanksgiving.",
    "referenceId": "6dd9b69663d84fdc4ae2d67a094da49e",
    "date_created": "1523659180",
    "date_modified": "1524271751",
    "tags": "",
    "sourceId": "6",
    "status": "approved",
    "visibility": "1",
    "VV_VI": "3",
    "engagement_score": null,
    "conversion_score": "25",
    "CVV_VI": null,
    "video_type": null,
    "user_id": "0",
    "product_category": null,
    "id": "159002722",
    "loginId": "1759121",
    "entityType": "1",
    "titleTextEncoded": "ANDREA-WARNER10",
    "category": "",
    "tvp_profiles": [],
    "tvp_profiles_manual": "",
    "tvp_profiles_maxscore": "",
    "VIDEO_LENGTH": "SHORT",
    "duration": "57",
    "settings": "",
    "asset": {
        "user": {
            "firstName": "",
            "lastName": "",
            "emailAddress": ""
        },
        "videoMeta": {
            "duration": "57",
            "width": 854,
            "height": 480
        },
        "mediaDuration": "57",
        "prettyDuration": "00:00:57",
        "thumbnailUrl": "\/\/v.tvpage.com\/1759121\/159002722\/cbee3\/thumb-6dd9b69663d84fdc4ae2d67a094da49e-00001.jpg",
        "type": "mp4",
        "dashUrl": "\/\/v.tvpage.com\/1759121\/159002722\/cbee3\/media.mpd",
        "hlsUrl": "\/\/v.tvpage.com\/1759121\/159002722\/cbee3\/media.m3u8",
        "uploadAsset": false,
        "quality": "",
        "sources": [
            {
                "file": "\/\/v.tvpage.com\/1759121\/159002722\/cbee3\/1080p_media.mp4",
                "quality": "1080p",
                "mime": "video\/mp4",
                "width": 854,
                "height": 480
            },
            {
                "file": "\/\/v.tvpage.com\/1759121\/159002722\/cbee3\/720p_media.mp4",
                "quality": "720p",
                "mime": "video\/mp4",
                "width": 854,
                "height": 480
            },
            {
                "file": "\/\/v.tvpage.com\/1759121\/159002722\/cbee3\/480p_media.mp4",
                "quality": "480p",
                "mime": "video\/mp4",
                "width": 854,
                "height": 480
            },
            {
                "file": "\/\/v.tvpage.com\/1759121\/159002722\/cbee3\/360p_media.mp4",
                "quality": "360p",
                "mime": "video\/mp4",
                "width": 640,
                "height": 360
            },
            {
                "file": "\/\/v.tvpage.com\/1759121\/159002722\/cbee3\/240p_media.mp4",
                "quality": "240p",
                "mime": "video\/mp4",
                "width": 320,
                "height": 180
            }
        ]
    },
    "transcripts": "",
    "metrics_statistics": "{\"VV_VI\":{\"engagement_score\":{\"lastUpdatedDate\":\"2018-06-16\"}},\"CVV_VI\":{\"conversion_score\":{\"lastUpdatedDate\":\"2018-06-18\"}}}",
    "tvp_enhanced_search": null,
    "tvp_enhanced_anti": null,
    "tvp_enhanced_brand": null,
    "tvp_enhanced_video_images": null,
    "tvp_enhanced_transcript": null
}