{
    "title": "LYDIA KIRSCH- The Statement Top",
    "description": "Lydia loves the statement top because they're feminine with a men twist",
    "referenceId": "15e9f29239a58ab16b67165af636b6df",
    "date_created": "1523984812",
    "date_modified": "1524271091",
    "tags": "",
    "sourceId": "6",
    "status": "approved",
    "visibility": "1",
    "VV_VI": "28",
    "engagement_score": "3",
    "conversion_score": null,
    "CVV_VI": null,
    "video_type": null,
    "user_id": "0",
    "product_category": null,
    "id": "160962634",
    "loginId": "1759121",
    "entityType": "1",
    "titleTextEncoded": "LYDIA-KIRSCH",
    "category": "",
    "tvp_profiles": [],
    "tvp_profiles_manual": "",
    "tvp_profiles_maxscore": "",
    "VIDEO_LENGTH": "SHORT",
    "duration": "107",
    "settings": "",
    "asset": {
        "user": {
            "firstName": "",
            "lastName": "",
            "emailAddress": ""
        },
        "videoMeta": {
            "duration": "107",
            "width": 854,
            "height": 480
        },
        "mediaDuration": "107",
        "prettyDuration": "00:01:47",
        "thumbnailUrl": "\/\/v.tvpage.com\/1759121\/160962634\/ac696\/thumb-15e9f29239a58ab16b67165af636b6df-00002.jpg",
        "type": "mp4",
        "dashUrl": "\/\/v.tvpage.com\/1759121\/160962634\/ac696\/media.mpd",
        "hlsUrl": "\/\/v.tvpage.com\/1759121\/160962634\/ac696\/media.m3u8",
        "uploadAsset": false,
        "quality": "",
        "sources": [
            {
                "file": "\/\/v.tvpage.com\/1759121\/160962634\/ac696\/1080p_media.mp4",
                "quality": "1080p",
                "mime": "video\/mp4",
                "width": 854,
                "height": 480
            },
            {
                "file": "\/\/v.tvpage.com\/1759121\/160962634\/ac696\/720p_media.mp4",
                "quality": "720p",
                "mime": "video\/mp4",
                "width": 854,
                "height": 480
            },
            {
                "file": "\/\/v.tvpage.com\/1759121\/160962634\/ac696\/480p_media.mp4",
                "quality": "480p",
                "mime": "video\/mp4",
                "width": 854,
                "height": 480
            },
            {
                "file": "\/\/v.tvpage.com\/1759121\/160962634\/ac696\/360p_media.mp4",
                "quality": "360p",
                "mime": "video\/mp4",
                "width": 640,
                "height": 360
            },
            {
                "file": "\/\/v.tvpage.com\/1759121\/160962634\/ac696\/240p_media.mp4",
                "quality": "240p",
                "mime": "video\/mp4",
                "width": 320,
                "height": 180
            }
        ]
    },
    "transcripts": "",
    "metrics_statistics": {
        "VV_VI": {
            "lastUpdatedDate": "2018-06-18"
        }
    },
    "tvp_enhanced_search": null,
    "tvp_enhanced_anti": null,
    "tvp_enhanced_brand": null,
    "tvp_enhanced_video_images": null,
    "tvp_enhanced_transcript": null
}