{
    "title": "Summer '18 Glow Up - converted with Clipchamp",
    "description": "Check out the products that give me that glow that turns heads",
    "referenceId": "86fd2a83db5e5a1252f64bd5aec83ca6",
    "date_created": "1529150536",
    "date_modified": "1529151350",
    "tags": "",
    "sourceId": "6",
    "status": "approved",
    "visibility": "1",
    "VV_VI": null,
    "engagement_score": null,
    "conversion_score": null,
    "CVV_VI": null,
    "video_type": null,
    "user_id": "213271",
    "product_category": null,
    "id": "164926684",
    "loginId": "1759121",
    "entityType": "1",
    "titleTextEncoded": "summer-18-glow-up-converted-with-clipchamp",
    "category": null,
    "tvp_profiles": null,
    "tvp_profiles_manual": null,
    "tvp_profiles_maxscore": null,
    "VIDEO_LENGTH": "SHORT",
    "duration": "87",
    "settings": null,
    "asset": {
        "videoMeta": {
            "duration": "87",
            "width": 1920,
            "height": 1080
        },
        "mediaDuration": "87",
        "prettyDuration": "00:01:27",
        "thumbnailUrl": "\/\/v.tvpage.com\/1759121\/164926684\/2ab1b\/thumb-86fd2a83db5e5a1252f64bd5aec83ca6-00002.jpg",
        "type": "mp4",
        "assetId": "164926684",
        "assetTitle": "Summer '18 Glow Up - converted with Clipchamp",
        "assetTitleTextEncoded": "summer-18-glow-up-converted-with-clipchamp",
        "loginId": "1759121",
        "analyticsObj": {
            "pg": 0,
            "vd": "164926684",
            "li": "1759121"
        },
        "sources": [
            {
                "file": "\/\/v.tvpage.com\/1759121\/164926684\/2ab1b\/1080p_media.mp4",
                "quality": "1080p",
                "mime": "video\/mp4",
                "width": 1920,
                "height": 1080
            },
            {
                "file": "\/\/v.tvpage.com\/1759121\/164926684\/2ab1b\/720p_media.mp4",
                "quality": "720p",
                "mime": "video\/mp4",
                "width": 1280,
                "height": 720
            },
            {
                "file": "\/\/v.tvpage.com\/1759121\/164926684\/2ab1b\/480p_media.mp4",
                "quality": "480p",
                "mime": "video\/mp4",
                "width": 854,
                "height": 480
            },
            {
                "file": "\/\/v.tvpage.com\/1759121\/164926684\/2ab1b\/360p_media.mp4",
                "quality": "360p",
                "mime": "video\/mp4",
                "width": 640,
                "height": 360
            },
            {
                "file": "\/\/v.tvpage.com\/1759121\/164926684\/2ab1b\/240p_media.mp4",
                "quality": "240p",
                "mime": "video\/mp4",
                "width": 320,
                "height": 180
            }
        ],
        "dashUrl": "\/\/v.tvpage.com\/1759121\/164926684\/2ab1b\/media.mpd",
        "hlsUrl": "\/\/v.tvpage.com\/1759121\/164926684\/2ab1b\/media.m3u8"
    },
    "transcripts": null,
    "metrics_statistics": null,
    "tvp_enhanced_search": null,
    "tvp_enhanced_anti": null,
    "tvp_enhanced_brand": null,
    "tvp_enhanced_video_images": null,
    "tvp_enhanced_transcript": null
}