{
    "title": "Macy's Woman Palm Print Maxi Dress",
    "description": "Angelica Renee is here to show you all the fashion Macy's Womans has to offer for our stylish plus size ladies!",
    "referenceId": "592697678f8e49fb5fd7678f59b1743b",
    "date_created": "1527538824",
    "date_modified": "1527869968",
    "tags": "",
    "sourceId": "6",
    "status": "approved",
    "visibility": "1",
    "VV_VI": "13",
    "engagement_score": "1",
    "conversion_score": "50",
    "CVV_VI": null,
    "video_type": null,
    "user_id": "213259",
    "product_category": "women",
    "id": "164597061",
    "loginId": "1759121",
    "entityType": "1",
    "titleTextEncoded": "img-1192",
    "category": null,
    "tvp_profiles": [],
    "tvp_profiles_manual": null,
    "tvp_profiles_maxscore": null,
    "VIDEO_LENGTH": "SHORT",
    "duration": "23",
    "settings": null,
    "asset": {
        "videoMeta": {
            "duration": "23",
            "width": 320,
            "height": 568
        },
        "mediaDuration": "23",
        "prettyDuration": "00:00:23",
        "thumbnailUrl": "\/\/v.tvpage.com\/1759121\/164597061\/fb233\/thumb-592697678f8e49fb5fd7678f59b1743b-00002.jpg",
        "type": "mp4",
        "dashUrl": "\/\/v.tvpage.com\/1759121\/164597061\/fb233\/media.mpd",
        "hlsUrl": "\/\/v.tvpage.com\/1759121\/164597061\/fb233\/media.m3u8",
        "assetId": "164597061",
        "assetTitle": "Time to take out our dresses",
        "assetTitleTextEncoded": "img-1192",
        "loginId": "1759121",
        "analyticsObj": {
            "pg": 0,
            "vd": "164597061",
            "li": "1759121"
        },
        "uploadAsset": false,
        "quality": "",
        "sources": [
            {
                "file": "\/\/v.tvpage.com\/1759121\/164597061\/fb233\/1080p_media.mp4",
                "quality": "1080p",
                "mime": "video\/mp4",
                "width": 320,
                "height": 568
            },
            {
                "file": "\/\/v.tvpage.com\/1759121\/164597061\/fb233\/720p_media.mp4",
                "quality": "720p",
                "mime": "video\/mp4",
                "width": 320,
                "height": 568
            },
            {
                "file": "\/\/v.tvpage.com\/1759121\/164597061\/fb233\/480p_media.mp4",
                "quality": "480p",
                "mime": "video\/mp4",
                "width": 270,
                "height": 480
            },
            {
                "file": "\/\/v.tvpage.com\/1759121\/164597061\/fb233\/360p_media.mp4",
                "quality": "360p",
                "mime": "video\/mp4",
                "width": 202,
                "height": 360
            },
            {
                "file": "\/\/v.tvpage.com\/1759121\/164597061\/fb233\/240p_media.mp4",
                "quality": "240p",
                "mime": "video\/mp4",
                "width": 136,
                "height": 240
            }
        ]
    },
    "transcripts": null,
    "metrics_statistics": "{\"VV_VI\":{\"lastUpdatedDate\":\"2018-06-18\"},\"CVV_VI\":{\"conversion_score\":{\"lastUpdatedDate\":\"2018-06-18\"}}}",
    "tvp_enhanced_search": null,
    "tvp_enhanced_anti": null,
    "tvp_enhanced_brand": null,
    "tvp_enhanced_video_images": "",
    "tvp_enhanced_transcript": null
}