{
    "id": "661",
    "first_name": "Matt",
    "last_name": "Test",
    "data": {
        "profilePhoto": null,
        "job_title": "ads"
    },
    "last_login_timestamp": "1525286795",
    "created_timestamp": null,
    "modified_timestamp": "2018-05-02 18:40:58",
    "login_id": "1759121",
    "user_id": "661",
    "role_id": "2",
    "status": "2",
    "fullName": "Matt Test",
    "profile_picture": null,
    "titleTextEncoded": "matt-test",
    "title": "Matt Test",
    "videos_count": "0"
}